emptys/__init__.py
emptys/encoding.py
emptys/loader.py
emptys/missing_values.py
emptys/outlier_detection.py
emptys/split_dataset.py
emptys-1.1.dist-info/METADATA
emptys-1.1.dist-info/WHEEL
emptys-1.1.dist-info/top_level.txt
emptys-1.1.dist-info/RECORD
